{
  "questions": [
    {
      "id": "A1111111-1111-1111-1111-111111111111",
      "text": "Which company created Swift?",
      "answers": ["Apple", "Google", "Microsoft", "IBM"],
      "correctIndex": 0
    },
    {
      "id": "B2222222-2222-2222-2222-222222222222",
      "text": "Which platform is this game running on?",
      "answers": ["tvOS", "watchOS", "macOS", "visionOS"],
      "correctIndex": 0
    },
    {
      "id": "C3333333-3333-3333-3333-333333333333",
      "text": "What protocol are we using for controllers?",
      "answers": ["Bluetooth", "HTTP", "WebSocket", "NFC"],
      "correctIndex": 2
    },
    {
      "id": "D4444444-4444-4444-4444-444444444444",
      "text": "SwiftUI was introduced in which year?",
      "answers": ["2018", "2019", "2020", "2021"],
      "correctIndex": 1
    },
    {
      "id": "E5555555-5555-5555-5555-555555555555",
      "text": "What is the capital of France?",
      "answers": ["London", "Berlin", "Paris", "Madrid"],
      "correctIndex": 2
    }
  ]
}
